Workbook

Sheet KPI Dashboard
A1: SALES PERFORMANCE DASHBOARD - 2024
A3: KEY PERFORMANCE INDICATORS | E3: REGIONAL PERFORMANCE
A4: Total Revenue | B4: =SUM('Sales Data'!H:H) | E4: Region | F4: Revenue | G4: Profit | H4: Margin %
A5: Total Profit | B5: =SUM('Sales Data'!J:J) | E5: North | F5: =SUMIF('Sales Data'!E:E,"North",'Sales Data'!H:H) | G5: =SUMIF('Sales Data'!E:E,"North",'Sales Data'!J:J) | H5: =G5/F5
A6: Profit Margin % | B6: =B5/B4 | E6: South | F6: =SUMIF('Sales Data'!E:E,"South",'Sales Data'!H:H) | G6: =SUMIF('Sales Data'!E:E,"South",'Sales Data'!J:J) | H6: =G6/F6
A7: Avg Order Value | B7: =AVERAGE('Sales Data'!H:H) | E7: East | F7: =SUMIF('Sales Data'!E:E,"East",'Sales Data'!H:H) | G7: =SUMIF('Sales Data'!E:E,"East",'Sales Data'!J:J) | H7: =G7/F7
A8: Total Orders | B8: =COUNTA('Sales Data'!B:B)-1 | E8: West | F8: =SUMIF('Sales Data'!E:E,"West",'Sales Data'!H:H) | G8: =SUMIF('Sales Data'!E:E,"West",'Sales Data'!J:J) | H8: =G8/F8
A10: PRODUCT PERFORMANCE
A11: Product | B11: Category | C11: Units Sold | D11: Revenue | E11: Profit | F11: Margin % | G11: vs Target
A12: Product A | B12: Electronics | C12: =SUMIF('Sales Data'!C:C,A12,'Sales Data'!F:F) | D12: =SUMIF('Sales Data'!C:C,A12,'Sales Data'!H:H) | E12: =SUMIF('Sales Data'!C:C,A12,'Sales Data'!J:J) | F12: =E12/D12 | G12: =F12-Products!E2
A13: Product B | B13: Furniture | C13: =SUMIF('Sales Data'!C:C,A13,'Sales Data'!F:F) | D13: =SUMIF('Sales Data'!C:C,A13,'Sales Data'!H:H) | E13: =SUMIF('Sales Data'!C:C,A13,'Sales Data'!J:J) | F13: =E13/D13 | G13: =F13-Products!E3
A14: Product C | B14: Office Supplies | C14: =SUMIF('Sales Data'!C:C,A14,'Sales Data'!F:F) | D14: =SUMIF('Sales Data'!C:C,A14,'Sales Data'!H:H) | E14: =SUMIF('Sales Data'!C:C,A14,'Sales Data'!J:J) | F14: =E14/D14 | G14: =F14-Products!E4
A15: Product D | B15: Electronics | C15: =SUMIF('Sales Data'!C:C,A15,'Sales Data'!F:F) | D15: =SUMIF('Sales Data'!C:C,A15,'Sales Data'!H:H) | E15: =SUMIF('Sales Data'!C:C,A15,'Sales Data'!J:J) | F15: =E15/D15 | G15: =F15-Products!E5
A16: Product E | B16: Furniture | C16: =SUMIF('Sales Data'!C:C,A16,'Sales Data'!F:F) | D16: =SUMIF('Sales Data'!C:C,A16,'Sales Data'!H:H) | E16: =SUMIF('Sales Data'!C:C,A16,'Sales Data'!J:J) | F16: =E16/D16 | G16: =F16-Products!E6

Sheet Sales Data
A1: Date | B1: Order_ID | C1: Product | D1: Category | E1: Region | F1: Quantity | G1: Unit_Price | H1: Revenue | I1: Cost | J1: Profit
A2: 45292 | B2: ORD-10001 | C2: Product D | D2: Electronics | E2: North | F2: 8 | G2: 2708.92 | H2: 21671.34 | I2: 12426.41 | J2: 9244.93
A3: 45292 | B3: ORD-10002 | C3: Product C | D3: Office Supplies | E3: East | F3: 8 | G3: 525.3 | H3: 4202.43 | I3: 2401.39 | J3: 1801.03
A4: 45292 | B4: ORD-10003 | C4: Product C | D4: Office Supplies | E4: South | F4: 5 | G4: 509.52 | H4: 2547.61 | I4: 1719.3 | J4: 828.31
A5: 45292 | B5: ORD-10004 | C5: Product B | D5: Furniture | E5: West | F5: 5 | G5: 950.44 | H5: 4752.22 | I5: 3049.73 | J5: 1702.49
A6: 45292 | B6: ORD-10005 | C6: Product E | D6: Furniture | E6: West | F6: 9 | G6: 1675.01 | H6: 15075.12 | I6: 9674.88 | J6: 5400.24
A7: 45292 | B7: ORD-10006 | C7: Product B | D7: Furniture | E7: West | F7: 3 | G7: 906.8 | H7: 2720.39 | I7: 1897.43 | J7: 822.96
A8: 45292 | B8: ORD-10007 | C8: Product A | D8: Electronics | E8: East | F8: 5 | G8: 1480.17 | H8: 7400.83 | I8: 4259.76 | J8: 3141.07
A9: 45292 | B9: ORD-10008 | C9: Product B | D9: Furniture | E9: West | F9: 9 | G9: 1015.1 | H9: 9135.94 | I9: 6132.59 | J9: 3003.35
A10: 45292 | B10: ORD-10009 | C10: Product A | D10: Electronics | E10: South | F10: 5 | G10: 1175.15 | H10: 5875.77 | I10: 3444.11 | J10: 2431.67
A11: 45292 | B11: ORD-10010 | C11: Product D | D11: Electronics | E11: East | F11: 8 | G11: 2299.62 | H11: 18396.92 | I11: 12627.61 | J11: 5769.31
A12: 45292 | B12: ORD-10011 | C12: Product D | D12: Electronics | E12: South | F12: 8 | G12: 2284.51 | H12: 18276.04 | I12: 11217.35 | J12: 7058.7
A13: 45293 | B13: ORD-10012 | C13: Product B | D13: Furniture | E13: West | F13: 6 | G13: 841.58 | H13: 5049.47 | I13: 3415.17 | J13: 1634.3
... A3446: 45657 | B3446: ORD-13445 | C3446: Product C | D3446: Office Supplies | E3446: South | F3446: 3 | G3446: 396.26 | H3446: 1188.79 | I3446: 804.36 | J3446: 384.43

Sheet Products
A1: Product_ID | B1: Product_Name | C1: Category | D1: Standard_Price | E1: Target_Margin
A2: P001 | B2: Product A | C2: Electronics | D2: 1200 | E2: 0.35
A3: P002 | B3: Product B | C3: Furniture | D3: 850 | E3: 0.4
A4: P003 | B4: Product C | C4: Office Supplies | D4: 450 | E4: 0.45
A5: P004 | B5: Product D | C5: Electronics | D5: 2100 | E5: 0.3
A6: P005 | B6: Product E | C6: Furniture | D6: 1600 | E6: 0.32

Sheet Regions
A1: Region | B1: Sales_Manager | C1: Territory_Size | D1: Sales_Target_Monthly
A2: North | B2: John Smith | C2: Large | D2: 500000
A3: South | B3: Sarah Johnson | C3: Medium | D3: 350000
A4: East | B4: Michael Chen | C4: Large | D4: 450000
A5: West | B5: Emily Davis | C5: Small | D5: 300000
